ln_ports/__init__.py
ln_ports/compounds.py
ln_ports/compounds_dims.py
ln_ports/compounds_typed.py
ln_ports/primitives.py
ln_ports/tuples.py
ln_ports/tuples_dims.py
LN_Ports-1.0.0.dist-info/AUTHORS.rst
LN_Ports-1.0.0.dist-info/LICENSE
LN_Ports-1.0.0.dist-info/METADATA
LN_Ports-1.0.0.dist-info/WHEEL
LN_Ports-1.0.0.dist-info/top_level.txt
LN_Ports-1.0.0.dist-info/zip-safe
LN_Ports-1.0.0.dist-info/RECORD
